asl_mutation/ASLMutation.py
asl_mutation/__init__.py
ASLMutation-1.1.0.dist-info/LICENSE
ASLMutation-1.1.0.dist-info/METADATA
ASLMutation-1.1.0.dist-info/WHEEL
ASLMutation-1.1.0.dist-info/top_level.txt
ASLMutation-1.1.0.dist-info/RECORD
